sami_cli/__init__.py
sami_cli/auth.py
sami_cli/cli.py
sami_cli/client.py
sami_cli/config.py
sami_cli/download.py
sami_cli/exceptions.py
sami_cli/models.py
sami_cli/upload.py
sami_cli-0.1.2.dist-info/METADATA
sami_cli-0.1.2.dist-info/WHEEL
sami_cli-0.1.2.dist-info/entry_points.txt
sami_cli-0.1.2.dist-info/top_level.txt
sami_cli-0.1.2.dist-info/RECORD
