Metadata-Version: 2.4
Name: sami-cli
Version: 0.1.2
Summary: Python SDK and CLI for SAMI Dataset Distribution Platform
Author: Dextero Robotics
License: MIT
Project-URL: Homepage, https://github.com/Neotix-Robotics/sami-cli
Project-URL: Documentation, https://github.com/Neotix-Robotics/sami-cli#readme
Project-URL: Repository, https://github.com/Neotix-Robotics/sami-cli
Project-URL: Issues, https://github.com/Neotix-Robotics/sami-cli/issues
Keywords: robotics,datasets,lerobot,machine-learning,ai
Classifier: Development Status :: 4 - Beta
Classifier: Environment :: Console
Classifier: Intended Audience :: Developers
Classifier: Intended Audience :: Science/Research
Classifier: License :: OSI Approved :: MIT License
Classifier: Operating System :: OS Independent
Classifier: Programming Language :: Python :: 3
Classifier: Programming Language :: Python :: 3.9
Classifier: Programming Language :: Python :: 3.10
Classifier: Programming Language :: Python :: 3.11
Classifier: Programming Language :: Python :: 3.12
Classifier: Topic :: Scientific/Engineering :: Artificial Intelligence
Classifier: Topic :: Software Development :: Libraries :: Python Modules
Requires-Python: >=3.9
Requires-Dist: requests>=2.28.0
Requires-Dist: tqdm>=4.65.0
Provides-Extra: dev
Requires-Dist: pytest>=7.0.0; extra == "dev"
Requires-Dist: pytest-cov>=4.0.0; extra == "dev"
Requires-Dist: pytest-mock>=3.10.0; extra == "dev"
